rapid_pe/__init__.py
rapid_pe/amrlib.py
rapid_pe/common_cl.py
rapid_pe/dagutils.py
rapid_pe/effectiveFisher.py
rapid_pe/factored_likelihood.py
rapid_pe/lalsimutils.py
rapid_pe/mcsampler.py
rapid_pe/sph_harmonics.py
rapid_pe/statutils.py
rapid_pe/synchlib.py
rapid_pe/xmlutils.py
rapid_pe/tests/__init__.py
rapid_pe/tests/test_common_cl.py
rapid_pe-0.0.3.data/scripts/rapidpe_calculate_overlap
rapid_pe-0.0.3.data/scripts/rapidpe_compute_intrinsic_fisher
rapid_pe-0.0.3.data/scripts/rapidpe_compute_intrinsic_grid
rapid_pe-0.0.3.data/scripts/rapidpe_create_event_dag
rapid_pe-0.0.3.data/scripts/rapidpe_integrate_extrinsic_likelihood
rapid_pe-0.0.3.data/scripts/rapidpe_triangulation
rapid_pe-0.0.3.dist-info/COPYING
rapid_pe-0.0.3.dist-info/METADATA
rapid_pe-0.0.3.dist-info/WHEEL
rapid_pe-0.0.3.dist-info/top_level.txt
rapid_pe-0.0.3.dist-info/RECORD
